scr/Multiplicador4bits.v
module Multiplicador4bits(
    input  wire       init,    // señal de inicio (nivel o pulso) tratada síncronamente
    input  wire       clk,
    input  wire       rst,     // reset síncrono, activo 1
    input  wire [3:0] MD,      // multiplicando (3 bits)
    input  wire [3:0] MR,      // multiplicador (3 bits)
    output reg  [7:0] PP,      // producto parcial / resultado (6 bits)
    output reg        done
    );

    // Estados
    localparam [2:0] START     = 3'b000;
    localparam [2:0] CHECK     = 3'b001;
    localparam [2:0] ADD       = 3'b010;
    localparam [2:0] SHIFT     = 3'b011;
    localparam [2:0] END_STATE = 3'b100;

    reg [2:0] fsm_state;
    reg [2:0] next_state;

    reg [7:0] A;        // acumulador desplazable (A << 1 cada SHIFT)
    reg [3:0] B;        // multiplicador (se desplaza a la derecha)
    reg [1:0] iter;     // cuenta 0..2 (3 iteraciones)

    wire LSB_B = B[0];

    // Lógica combinacional de transición (NO considera init aquí;
    // el reinicio/arranque por init se maneja síncronamente)
    always @(*) begin
        next_state = fsm_state; // default
        case (fsm_state)
            START:     next_state = START; // permanecer en START hasta que se pulse init (síncrono)
            CHECK:     next_state = (LSB_B == 1'b1) ? ADD : SHIFT;
            ADD:       next_state = SHIFT;
            SHIFT:     next_state = (iter == 2'd3) ? END_STATE : CHECK;
            END_STATE: next_state = END_STATE;
            default:   next_state = START;
        endcase
    end

    // Lógica secuencial: reset síncrono y prioridad síncrona a init
    always @(posedge clk) begin
        if (rst) begin
            // reset síncrono: dejar todo en estado inicial
            fsm_state <= START;
            PP        <= 8'd0;
            A         <= 8'd0;
            B         <= 4'd0;
            iter      <= 2'd0;
            done      <= 1'b0;
        end else if (init) begin
            // Opción B: FORZAR reinicio/recarga síncrona en el siguiente flanco de reloj.
            // Colocamos la FSM en CHECK para comenzar la ejecución inmediatamente.
            fsm_state <= CHECK;
            PP        <= 8'd0;
            A         <= {4'b0000, MD}; // A inicia con MD en los bits bajos
            B         <= MR;
            iter      <= 2'd0;
            done      <= 1'b0;
        end else begin
            // comportamiento normal
            fsm_state <= next_state;

            case (fsm_state)
                START: begin
                    // en esta versión START se usa principalmente después de reset;
                    // no hacemos carga aquí porque init lo maneja síncronamente.
                    done <= 1'b0;
                end

                CHECK: begin
                    // decisión en combinacional; aquí no hay asignaciones específicas.
                    // dejamos las señales tal como están.
                end

                ADD: begin
                    // sumar A (6 bits) a PP
                    PP <= PP + A;
                end

                SHIFT: begin
                    // desplazar A a la izquierda (multiplica por 2) y B a la derecha
                    A    <= A << 1;
                    B    <= B >> 1;
                    iter <= iter + 2'd1;
                end

                END_STATE: begin
                    // indicar final; done se mantiene hasta que se pulse init o rst
                    done <= 1'b1;
                end

                default: begin
                    // seguridad: no hacer nada
                end
            endcase
        end
    end

endmodule

scr/ALU.v
//`include "scr\suma4bits.v"
`include "scr\Resta4bits.v"
`include "scr\Multiplicador4bits.v"
`include "scr\Mover_Izquierda.v"
`include "scr\ModuloXor.v"

module adder4_if (
    input  wire [3:0] A, B,
    output wire [3:0] S
);

    suma4bits u_add (.A(A), .B(B), .Cin(1'b0), .S(S), .Cout());

endmodule

module sub4_if (
    input  wire [3:0] A, B,
    output wire [3:0] D,
    output wire Overflow
);
    
    Resta4bits u_sub (.A(A), .B(B), .D(D), .Overflow(Overflow), .Negative(), .Zero()); 

endmodule

module xor4_if (
    input  wire [3:0] A, B,
    output wire [3:0] X
);
    xor_1 b0 (.a(A[0]), .b(B[0]), .z(X[0]));
    xor_1 b1 (.a(A[1]), .b(B[1]), .z(X[1]));
    xor_1 b2 (.a(A[2]), .b(B[2]), .z(X[2]));
    xor_1 b3 (.a(A[3]), .b(B[3]), .z(X[3]));
endmodule

module shl4_if (
    input  wire [3:0] A,
    input  wire [1:0] B,
    output wire [3:0] E
);
    Mover_Izquierda u_sh (.A(A), .B(B), .E(E)); 
endmodule

module mul4_if (
    input  wire       clk,
    input  wire       rst,
    input  wire       init,        
    input  wire [3:0] A, B,        
    output wire [7:0] P,           
    output wire       done         
);
    Multiplicador4bits u_mul (
        .init(init),
        .clk (clk),
        .rst (rst),
        .MD  (A),
        .MR  (B),
        .PP  (P),
        .done(done)
    );
endmodule

module alu4 #(
    parameter N = 4,
    parameter M = 8
) (
    input  wire           clk,
    input  wire           rst,          // added: to drive the sequential multiplier
    input  wire           init,         // for non-MUL capture; also used to start MUL
    input  wire [N-1:0]   A,
    input  wire [N-1:0]   B,
    input  wire [2:0]     opcode,       // 000 add, 001 sub, 010 xor, 011 shl, 100 mul
    output reg  [M-1:0]   Y,
    output reg            overflow,
    output reg            zero
);

    wire [3:0] sum4, diff4, xor4, shl4;
    wire [M-1:0] prod8;   // 8-bit product
    wire         ovf_sub; // from subtractor
    wire         mul_done;

    // --- Instantiate operators ---
    adder4_if u_add  (.A(A[3:0]), .B(B[3:0]),       .S(sum4));

    sub4_if   u_sub  (.A(A[3:0]), .B(B[3:0]),       .D(diff4), .Overflow(ovf_sub));

    xor4_if   u_xor  (.A(A[3:0]), .B(B[3:0]),       .X(xor4));

    shl4_if   u_shl  (.A(A[3:0]), .B(B[1:0]),       .E(shl4)); 

    // Start multiplier only when opcode==MUL
    wire init_mul = init & (opcode == 3'b100);
    mul4_if   u_mul  (.clk(clk), .rst(rst), .init(init_mul),
                      .A(A[3:0]), .B(B[3:0]), .P(prod8), .done(mul_done));

    // ---- Overflow rules (two's complement for add/sub) ----
    wire ovf_add = (A[N-1] == B[N-1]) && (sum4[N-1]  != A[N-1]);
    //wire ovf_sub = (A[N-1] != B[N-1]) && (diff4[N-1] != A[N-1]);
    wire ovf_mul = |prod8[7:4]; 

    // ---- Opcode-driven multiplexer (combinational) ----
    reg [M-1:0] y_sel;
    reg         ovf_sel;
    always @* begin
        y_sel   = {M{1'b0}};
        ovf_sel = 1'b0;
        case (opcode)
            3'b000: begin y_sel = {{(M-4){1'b0}}, sum4 }; ovf_sel = ovf_add; end
            3'b001: begin y_sel = {{(M-4){1'b0}}, diff4}; ovf_sel = ovf_sub; end
            3'b010: begin y_sel = {{(M-4){1'b0}}, xor4 }; ovf_sel = 1'b0;   end
            3'b011: begin y_sel = {{(M-4){1'b0}}, shl4 }; ovf_sel = 1'b0;   end
            3'b100: begin y_sel = prod8;                 ovf_sel = ovf_mul; end
            default: begin y_sel = {M{1'b0}};            ovf_sel = 1'b0;    end
        endcase
    end

        // ---- Output registers ----
    // Non-MUL ops: capture on init. MUL: capture on mul_done.
    always @(posedge clk) begin
        if (rst) begin
            Y <= {M{1'b0}}; overflow <= 1'b0; zero <= 1'b1;
        end else begin
            if (opcode != 3'b100) begin
                if (init) begin
                    Y <= y_sel; overflow <= ovf_sel; zero <= (y_sel == {M{1'b0}});
                end
            end else begin
                if (mul_done) begin
                    Y <= prod8; overflow <= ovf_mul; zero <= (prod8 == {M{1'b0}});
                end
            end
        end
    end
endmodule

scr/Mover_Izquierda.v
// shifter4_logical_right.v
module Mover_Izquierda (
    input  wire [3:0] A,
    input  wire [1:0] B,   // shift amount: 0..3
    output wire [3:0] E
);
    assign C = A << B;     
endmodule

scr/ModuloXor.v
module xor_1 (
    input  wire a,
    input  wire b,
    output wire z
);
    assign z = a ^ b;  
endmodule

/*
For N bits

module xorn #(
    parameter N = 8
) (
    input  wire [N-1:0] a,
    input  wire [N-1:0] b,
    output wire [N-1:0] z
);
    assign z = a ^ b;
endmodule
*/

scr/suma1bit.v
module suma1bit(
    input A,
    input B,
    input Cin,
    output S,
    output Cout
);

wire xor1;
wire and1;
wire and2;

assign xor1 = A ^ B;
assign and1 = A & B;
assign and2 = Cin & xor1;
assign S = Cin ^ xor1;
assign Cout =  and1 | and2;


endmodule

scr/suma4bits.v
`include "scr\suma1bit.v"

module suma4bits (
    input [3:0] A,
    input [3:0] B,
    input Cin,
    output [3:0] S,  
    output [4:0] ST,
    output  Cout
);

wire C0;
wire C1;
wire C2;

suma1bit bit0(.A(A[0]), .B(B[0]), .Cin(Cin), .S(S[0]), .Cout(C0));
suma1bit bit1(.A(A[1]), .B(B[1]), .Cin(C0), .S(S[1]), .Cout(C1));
suma1bit bit2(.A(A[2]), .B(B[2]), .Cin(C1), .S(S[2]), .Cout(C2));
suma1bit bit3(.A(A[3]), .B(B[3]), .Cin(C2), .S(S[3]), .Cout(Cout));

assign ST = {Cout, S};

endmodule

scr/Resta4bits.v
`include "scr\suma4bits.v"

// sub4b_signed.v
module Resta4bits(
    input  wire [3:0] A,
    input  wire [3:0] B,
    output wire [3:0] D,         // D = A - B  
    output wire       Overflow,  // Overflow del complemento a 2
    output wire       Negative,  // Avisa que es negativo
    output wire       Zero       // Avisa que dió 0
);
  wire [3:0] Bx = ~B;  // B negado
  wire       Cout;

  // Two’s-complement subtraction: A - B = A + (~B) + 1
  suma4bits u_add(.A(A), .B(Bx), .Cin(1'b1), .S(D), .Cout(Cout));

  // Signed overflow for subtraction:
  assign Overflow = (A[3] ^ B[3]) & (A[3] ^ D[3]);
  // Helpful CPU-like flags:
  assign Negative = D[3];
  assign Zero     = (D == 4'b0000);
endmodule

scr/ALU_tb.v
`include "scr\ALU.v" 
`timescale 1ns/1ps


module alu4_tb;

  // Clock / reset / init
  reg clk = 0;
  always #5 clk = ~clk;   // 100 MHz

  reg rst;
  reg init;

  // Inputs
  reg  [3:0] A, B;
  reg  [2:0] opcode;

  // Outputs
  wire [7:0] Y;
  wire       overflow;
  wire       zero;

  // Device Under Test
  alu4 dut (
    .clk(clk),
    .rst(rst),
    .init(init),
    .A(A),
    .B(B),
    .opcode(opcode),
    .Y(Y),
    .overflow(overflow),
    .zero(zero)
  );

  // Dumpfile only (no console prints)
  initial begin
    $dumpfile("alu4_tb.vcd");
    $dumpvars(0, alu4_tb);
  end

  // --- Helper tasks (no $display) ---

  // Non-MUL ops: ADD(000), SUB(001), XOR(010), SHL(011)
  task run_nonmul(input [2:0] opc, input [3:0] a, input [3:0] b);
  begin
    opcode = opc; A = a; B = b;
    @(posedge clk); init = 1'b1;
    @(posedge clk); init = 1'b0;  // ALU captures here for non-MUL
    // leave a little settling time in the waveform
    repeat (2) @(posedge clk);
  end
  endtask

  // MUL (100): wait for internal done handshake
  task run_mul(input [3:0] a, input [3:0] b);
  begin
    opcode = 3'b100; A = a; B = b;
    @(posedge clk); init = 1'b1;
    @(posedge clk); init = 1'b0;
    // Wait for the ALU's multiplier to finish (internal signal)
    wait (dut.mul_done === 1'b1);
    @(posedge clk);                 // one extra edge after capture
    repeat (1) @(posedge clk);
  end
  endtask

  // --- Stimulus sequence (probe cases only; comments show expectations) ---
  initial begin
    // Reset
    rst = 1'b1; init = 1'b0; opcode = 3'b000; A = 4'd0; B = 4'd0;
    repeat (2) @(posedge clk);
    rst = 1'b0;
    @(posedge clk);

    // ===== ADD (000) =====
    run_nonmul(3'b000, 4'sd7, 4'sd4);   // 7+4 = 11 (0x0B), ovf=0
    run_nonmul(3'b000, 4'sd7, 4'sd5);   // 7+5 = 12 (0x0C), ovf=1 in 4-bit 2's comp

    // ===== SUB (001) =====
    run_nonmul(3'b001, 4'sd3, 4'sd7);   // 3-7 = -4 (0xC), ovf=0
    run_nonmul(3'b001, -6,     4'sd3);  // -6-3 = -9 -> wraps to +7, ovf=1

    // ===== XOR (010) =====
    run_nonmul(3'b010, 4'b1010, 4'b0110); // 0xA ^ 0x6 = 0xC
    run_nonmul(3'b010, 4'b0101, 4'b0101); // 0x5 ^ 0x5 = 0x0 (zero=1)

    // ===== SHL (011) =====
    run_nonmul(3'b011, 4'b0011, 4'b0010); // 0x3 << 2 = 0xC
    run_nonmul(3'b011, 4'b1111, 4'b0011); // 0xF << 3 = 0x8

    // ===== MUL (100) =====
    run_mul(4'd9,  4'd7);   // 9*7  = 63 (0x3F); ovf relative to 4-bit low nibble
    run_mul(4'd15, 4'd15);  // 15*15 = 225 (0xE1)
    run_mul(4'd0,  4'd7);   // 0*7 = 0

    // Done
    #50 $finish;
  end

endmodule

build/alu4_tb.vcd
$date
	Wed Oct 08 17:50:53 2025
$end
$version
	Icarus Verilog
$end
$timescale
	1ps
$end
$scope module alu4_tb $end
$var wire 1 ! zero $end
$var wire 1 " overflow $end
$var wire 8 # Y [7:0] $end
$var reg 4 $ A [3:0] $end
$var reg 4 % B [3:0] $end
$var reg 1 & clk $end
$var reg 1 ' init $end
$var reg 3 ( opcode [2:0] $end
$var reg 1 ) rst $end
$scope module dut $end
$var wire 4 * A [3:0] $end
$var wire 4 + B [3:0] $end
$var wire 1 & clk $end
$var wire 1 ' init $end
$var wire 1 , init_mul $end
$var wire 3 - opcode [2:0] $end
$var wire 1 . ovf_add $end
$var wire 1 ) rst $end
$var wire 4 / shl4 [3:0] $end
$var wire 4 0 xor4 [3:0] $end
$var wire 4 1 sum4 [3:0] $end
$var wire 8 2 prod8 [7:0] $end
$var wire 1 3 ovf_sub $end
$var wire 1 4 ovf_mul $end
$var wire 1 5 mul_done $end
$var wire 4 6 diff4 [3:0] $end
$var parameter 32 7 M $end
$var parameter 32 8 N $end
$var reg 8 9 Y [7:0] $end
$var reg 1 " overflow $end
$var reg 1 : ovf_sel $end
$var reg 8 ; y_sel [7:0] $end
$var reg 1 ! zero $end
$scope module u_add $end
$var wire 4 < A [3:0] $end
$var wire 4 = B [3:0] $end
$var wire 4 > S [3:0] $end
$scope module u_add $end
$var wire 4 ? A [3:0] $end
$var wire 4 @ B [3:0] $end
$var wire 1 A Cin $end
$var wire 5 B ST [4:0] $end
$var wire 4 C S [3:0] $end
$var wire 1 D Cout $end
$var wire 1 E C2 $end
$var wire 1 F C1 $end
$var wire 1 G C0 $end
$scope module bit0 $end
$var wire 1 H A $end
$var wire 1 I B $end
$var wire 1 A Cin $end
$var wire 1 G Cout $end
$var wire 1 J S $end
$var wire 1 K and1 $end
$var wire 1 L and2 $end
$var wire 1 M xor1 $end
$upscope $end
$scope module bit1 $end
$var wire 1 N A $end
$var wire 1 O B $end
$var wire 1 G Cin $end
$var wire 1 F Cout $end
$var wire 1 P S $end
$var wire 1 Q and1 $end
$var wire 1 R and2 $end
$var wire 1 S xor1 $end
$upscope $end
$scope module bit2 $end
$var wire 1 T A $end
$var wire 1 U B $end
$var wire 1 F Cin $end
$var wire 1 E Cout $end
$var wire 1 V S $end
$var wire 1 W and1 $end
$var wire 1 X and2 $end
$var wire 1 Y xor1 $end
$upscope $end
$scope module bit3 $end
$var wire 1 Z A $end
$var wire 1 [ B $end
$var wire 1 E Cin $end
$var wire 1 D Cout $end
$var wire 1 \ S $end
$var wire 1 ] and1 $end
$var wire 1 ^ and2 $end
$var wire 1 _ xor1 $end
$upscope $end
$upscope $end
$upscope $end
$scope module u_mul $end
$var wire 4 ` A [3:0] $end
$var wire 4 a B [3:0] $end
$var wire 1 & clk $end
$var wire 1 , init $end
$var wire 1 ) rst $end
$var wire 1 5 done $end
$var wire 8 b P [7:0] $end
$scope module u_mul $end
$var wire 4 c MD [3:0] $end
$var wire 4 d MR [3:0] $end
$var wire 1 & clk $end
$var wire 1 , init $end
$var wire 1 ) rst $end
$var wire 1 e LSB_B $end
$var parameter 3 f ADD $end
$var parameter 3 g CHECK $end
$var parameter 3 h END_STATE $end
$var parameter 3 i SHIFT $end
$var parameter 3 j START $end
$var reg 8 k A [7:0] $end
$var reg 4 l B [3:0] $end
$var reg 8 m PP [7:0] $end
$var reg 1 5 done $end
$var reg 3 n fsm_state [2:0] $end
$var reg 2 o iter [1:0] $end
$var reg 3 p next_state [2:0] $end
$upscope $end
$upscope $end
$scope module u_shl $end
$var wire 4 q A [3:0] $end
$var wire 2 r B [1:0] $end
$var wire 4 s E [3:0] $end
$scope module u_sh $end
$var wire 4 t A [3:0] $end
$var wire 2 u B [1:0] $end
$var wire 4 v E [3:0] $end
$var wire 1 w C $end
$upscope $end
$upscope $end
$scope module u_sub $end
$var wire 4 x A [3:0] $end
$var wire 4 y B [3:0] $end
$var wire 1 3 Overflow $end
$var wire 4 z D [3:0] $end
$scope module u_sub $end
$var wire 4 { A [3:0] $end
$var wire 4 | B [3:0] $end
$var wire 4 } Bx [3:0] $end
$var wire 1 3 Overflow $end
$var wire 1 ~ Zero $end
$var wire 1 !" Negative $end
$var wire 4 "" D [3:0] $end
$var wire 1 #" Cout $end
$scope module u_add $end
$var wire 4 $" A [3:0] $end
$var wire 4 %" B [3:0] $end
$var wire 1 &" Cin $end
$var wire 5 '" ST [4:0] $end
$var wire 4 (" S [3:0] $end
$var wire 1 #" Cout $end
$var wire 1 )" C2 $end
$var wire 1 *" C1 $end
$var wire 1 +" C0 $end
$scope module bit0 $end
$var wire 1 ," A $end
$var wire 1 -" B $end
$var wire 1 &" Cin $end
$var wire 1 +" Cout $end
$var wire 1 ." S $end
$var wire 1 /" and1 $end
$var wire 1 0" and2 $end
$var wire 1 1" xor1 $end
$upscope $end
$scope module bit1 $end
$var wire 1 2" A $end
$var wire 1 3" B $end
$var wire 1 +" Cin $end
$var wire 1 *" Cout $end
$var wire 1 4" S $end
$var wire 1 5" and1 $end
$var wire 1 6" and2 $end
$var wire 1 7" xor1 $end
$upscope $end
$scope module bit2 $end
$var wire 1 8" A $end
$var wire 1 9" B $end
$var wire 1 *" Cin $end
$var wire 1 )" Cout $end
$var wire 1 :" S $end
$var wire 1 ;" and1 $end
$var wire 1 <" and2 $end
$var wire 1 =" xor1 $end
$upscope $end
$scope module bit3 $end
$var wire 1 >" A $end
$var wire 1 ?" B $end
$var wire 1 )" Cin $end
$var wire 1 #" Cout $end
$var wire 1 @" S $end
$var wire 1 A" and1 $end
$var wire 1 B" and2 $end
$var wire 1 C" xor1 $end
$upscope $end
$upscope $end
$upscope $end
$upscope $end
$scope module u_xor $end
$var wire 4 D" A [3:0] $end
$var wire 4 E" B [3:0] $end
$var wire 4 F" X [3:0] $end
$scope module b0 $end
$var wire 1 G" a $end
$var wire 1 H" b $end
$var wire 1 I" z $end
$upscope $end
$scope module b1 $end
$var wire 1 J" a $end
$var wire 1 K" b $end
$var wire 1 L" z $end
$upscope $end
$scope module b2 $end
$var wire 1 M" a $end
$var wire 1 N" b $end
$var wire 1 O" z $end
$upscope $end
$scope module b3 $end
$var wire 1 P" a $end
$var wire 1 Q" b $end
$var wire 1 R" z $end
$upscope $end
$upscope $end
$upscope $end
$scope task run_mul $end
$var reg 4 S" a [3:0] $end
$var reg 4 T" b [3:0] $end
$upscope $end
$scope task run_nonmul $end
$var reg 4 U" a [3:0] $end
$var reg 4 V" b [3:0] $end
$var reg 3 W" opc [2:0] $end
$upscope $end
$upscope $end
$enddefinitions $end
$comment Show the parameter values. $end
$dumpall
b0 j
b11 i
b100 h
b1 g
b10 f
b100 8
b1000 7
$end
#0
$dumpvars
bx W"
bx V"
bx U"
bx T"
bx S"
0R"
0Q"
0P"
0O"
0N"
0M"
0L"
0K"
0J"
0I"
0H"
0G"
b0 F"
b0 E"
b0 D"
1C"
1B"
0A"
0@"
1?"
0>"
1="
1<"
0;"
0:"
19"
08"
17"
16"
05"
04"
13"
02"
11"
10"
0/"
0."
1-"
0,"
1+"
1*"
1)"
b0 ("
b10000 '"
1&"
b1111 %"
b0 $"
1#"
b0 ""
0!"
1~
b1111 }
b0 |
b0 {
b0 z
b0 y
b0 x
0w
bz v
b0 u
b0 t
bz s
b0 r
b0 q
bx p
bx o
bx n
bx m
bx l
bx k
xe
b0 d
b0 c
bx b
b0 a
b0 `
0_
0^
0]
0\
0[
0Z
0Y
0X
0W
0V
0U
0T
0S
0R
0Q
0P
0O
0N
0M
0L
0K
0J
0I
0H
0G
0F
0E
0D
b0 C
b0 B
0A
b0 @
b0 ?
b0 >
b0 =
b0 <
b0 ;
0:
bx 9
b0 6
x5
x4
03
bx 2
b0 1
b0 0
bz /
0.
b0 -
0,
b0 +
b0 *
1)
b0 (
0'
0&
b0 %
b0 $
bx #
x"
x!
$end
#5000
0e
04
b0 p
05
b0 o
b0 l
b0 k
b0 2
b0 b
b0 m
b0 n
1!
0"
b0 #
b0 9
1&
#10000
0&
#15000
0)
1&
#20000
0&
#25000
1:
1.
1#"
0!"
1B"
0@"
1\
1)"
b1011 ;
1J
b1011 B
b1011 1
b1011 >
b1011 C
1P
1E
00"
1."
06"
14"
1<"
b10011 '"
0~
b11 6
b11 z
b11 ""
b11 ("
0:"
09"
1M
1S
1W
01"
1/"
07"
15"
1="
0;"
1I"
b11 0
b11 F"
1L"
1U
b1011 }
b1011 %"
1N"
1H
1N
1T
1w
1,"
12"
18"
1G"
1J"
1M"
b100 %
b100 +
b100 =
b100 @
b100 a
b100 d
b100 y
b100 |
b100 E"
b111 $
b111 *
b111 <
b111 ?
b111 `
b111 c
b111 q
b111 t
b111 x
b111 {
b111 $"
b111 D"
b100 V"
b111 U"
b0 W"
1&
#30000
0&
#35000
0!
1"
b1011 #
b1011 9
1'
1&
#40000
0&
#45000
0'
1&
#50000
0&
#55000
1&
#60000
0&
#65000
1V
1F
0~
14"
1R
0P
10"
b10010 '"
b10 6
b10 z
b10 ""
b10 ("
0."
1+"
b1100 B
b1100 1
b1100 >
b1100 C
0J
1G
11"
0/"
1:
b1100 ;
0w
0M
1K
0-"
b10 0
b10 F"
0I"
b1 r
b1 u
1I
b1010 }
b1010 %"
1H"
b101 %
b101 +
b101 =
b101 @
b101 a
b101 d
b101 y
b101 |
b101 E"
b101 V"
1&
#70000
0&
#75000
b1100 #
b1100 9
1'
1&
#80000
0&
#85000
0'
1&
#90000
0&
#95000
1&
#100000
0&
#105000
1.
0#"
1!"
0B"
1@"
16"
04"
1*"
1\
0)"
0R
1P
17"
05"
1X
b1010 B
b1010 1
b1010 >
b1010 C
0V
1E
0<"
b1100 '"
b1100 6
b1100 z
b1100 ""
b1100 ("
1:"
0S
1Q
03"
0L"
1Y
0W
0="
b100 0
b100 F"
1O"
b11 r
b11 u
1O
b1000 }
b1000 %"
1K"
0T
08"
0M"
0:
b1100 ;
b111 %
b111 +
b111 =
b111 @
b111 a
b111 d
b111 y
b111 |
b111 E"
b11 $
b11 *
b11 <
b11 ?
b11 `
b11 c
b11 q
b11 t
b11 x
b11 {
b11 $"
b11 D"
b1 (
b1 -
b111 V"
b11 U"
b1 W"
1&
#110000
0&
#115000
0"
1'
1&
#120000
0&
#125000
0'
1&
#130000
0&
#135000
1&
#140000
0&
#145000
1:
0*"
13
0)"
06"
14"
0E
0<"
1:"
0P
0D
0+"
0!"
0X
1V
1="
0.
1J
0G
0^
b1101 B
b1101 1
b1101 >
b1101 C
1\
00"
1."
b111 6
b111 z
b111 ""
b111 ("
0@"
b10111 '"
1#"
b111 ;
0Y
19"
0O"
1M
0K
1_
01"
0C"
1A"
1I"
b1001 0
b1001 F"
1R"
0U
b1100 }
b1100 %"
0N"
0H
1Z
0,"
1>"
0G"
1P"
b11 %
b11 +
b11 =
b11 @
b11 a
b11 d
b11 y
b11 |
b11 E"
b1010 $
b1010 *
b1010 <
b1010 ?
b1010 `
b1010 c
b1010 q
b1010 t
b1010 x
b1010 {
b1010 $"
b1010 D"
b11 V"
b1010 U"
1&
#150000
0&
#155000
1"
b111 #
b111 9
1'
1&
#160000
0&
#165000
0'
1&
#170000
0&
#175000
1&
#180000
0&
#185000
1*"
1D
16"
0~
04"
1^
0\
1+"
1E
10"
0."
b10100 '"
b100 6
b100 z
b100 ""
b100 ("
1:"
0J
1X
b10000 B
b0 1
b0 >
b0 C
0V
11"
0="
0M
1Y
1-"
09"
0I"
b1100 0
b1100 F"
1O"
b10 r
b10 u
0I
1U
b1001 }
b1001 %"
0H"
1N"
0:
b1100 ;
b110 %
b110 +
b110 =
b110 @
b110 a
b110 d
b110 y
b110 |
b110 E"
b10 (
b10 -
b110 V"
b10 W"
1&
#190000
0&
#195000
0"
b1100 #
b1100 9
1'
1&
#200000
0&
#205000
0'
1&
#210000
0&
#215000
1&
#220000
0&
#225000
1~
1.
1B"
1P
0D
1+"
1*"
1)"
0!"
1G
0F
0X
0V
0^
b1010 B
b1010 1
b1010 >
b1010 C
1\
03
10"
0."
16"
04"
1<"
0:"
b0 6
b0 z
b0 ""
b0 ("
0@"
b10000 '"
1#"
b0 ;
0-"
13"
1K
0Q
0Y
1W
0_
11"
0/"
17"
1="
1C"
0A"
0O"
b0 0
b0 F"
0R"
b1 r
b1 u
1I
0O
b1010 }
b1010 %"
1H"
0K"
1H
0N
1T
0Z
1,"
02"
18"
0>"
1G"
0J"
1M"
0P"
b101 %
b101 +
b101 =
b101 @
b101 a
b101 d
b101 y
b101 |
b101 E"
b101 $
b101 *
b101 <
b101 ?
b101 `
b101 c
b101 q
b101 t
b101 x
b101 {
b101 $"
b101 D"
b101 V"
b101 U"
1&
#230000
0&
#235000
1!
b0 #
b0 9
1'
1&
#240000
0&
#245000
0'
1&
#250000
0&
#255000
1&
#260000
0&
#265000
0.
1#"
0!"
1B"
0@"
0P
00"
1."
1V
0\
1*"
1)"
b101 B
b101 1
b101 >
b101 C
1J
0G
01"
1/"
1F
0E
16"
04"
1<"
b10001 '"
0~
b1 6
b1 z
b1 ""
b1 ("
0:"
1M
0K
1-"
03"
19"
b1 0
b1 F"
1I"
1Q
0W
17"
05"
1="
b10 r
b10 u
0I
1O
0U
b1101 }
b1101 %"
0H"
1K"
0N"
1N
0T
12"
08"
1J"
0M"
b0zzzz ;
b10 %
b10 +
b10 =
b10 @
b10 a
b10 d
b10 y
b10 |
b10 E"
b11 $
b11 *
b11 <
b11 ?
b11 `
b11 c
b11 q
b11 t
b11 x
b11 {
b11 $"
b11 D"
b11 (
b11 -
b10 V"
b11 U"
b11 W"
1&
#270000
0&
#275000
x!
b0zzzz #
b0zzzz 9
1'
1&
#280000
0&
#285000
0'
1&
#290000
0&
#295000
1&
#300000
0&
#305000
1*"
1D
16"
04"
1^
1P
10"
0."
1+"
1E
1!"
0J
1G
11"
0/"
1X
0V
b10010 B
b10 1
b10 >
b10 C
0\
03
0<"
1:"
0B"
b11100 '"
b1100 6
b1100 z
b1100 ""
b1100 ("
1@"
b0zzzz ;
0M
1K
0-"
0I"
1Y
1_
0="
1;"
0C"
1A"
1O"
b1100 0
b1100 F"
1R"
b11 r
b11 u
1I
b1100 }
b1100 %"
1H"
1T
1Z
18"
1>"
1M"
1P"
b11 %
b11 +
b11 =
b11 @
b11 a
b11 d
b11 y
b11 |
b11 E"
b1111 $
b1111 *
b1111 <
b1111 ?
b1111 `
b1111 c
b1111 q
b1111 t
b1111 x
b1111 {
b1111 $"
b1111 D"
b11 V"
b1111 U"
1&
#310000
0&
#315000
1'
1&
#320000
0&
#325000
0'
1&
#330000
0&
#335000
1&
#340000
0&
#345000
1D
13
1^
0\
1E
0!"
1X
0V
0*"
0@"
1R
b10000 B
b0 1
b0 >
b0 C
0P
1F
06"
14"
0<"
b10010 '"
b10 6
b10 z
b10 ""
b10 ("
0:"
0)"
09"
1S
0Q
07"
0="
0;"
b1110 0
b1110 F"
1L"
1U
b1000 }
b1000 %"
1N"
0N
0T
02"
08"
0J"
0M"
b0 ;
b111 %
b111 +
b111 =
b111 @
b111 a
b111 d
b111 y
b111 |
b111 E"
b1001 $
b1001 *
b1001 <
b1001 ?
b1001 `
b1001 c
b1001 q
b1001 t
b1001 x
b1001 {
b1001 $"
b1001 D"
b100 (
b100 -
b111 T"
b1001 S"
1&
#350000
0&
#355000
1,
1'
1&
#360000
0&
#365000
1e
b10 p
b111 l
b1001 k
b1 n
0,
0'
1&
#370000
0&
#375000
b11 p
b10 n
1&
#380000
0&
#385000
b1001 ;
b1 p
b1001 2
b1001 b
b1001 m
b11 n
1&
#390000
0&
#395000
b10 p
b1 o
b11 l
b10010 k
b1 n
1&
#400000
0&
#405000
b11 p
b10 n
1&
#410000
0&
#415000
1:
14
b11011 ;
b1 p
b11011 2
b11011 b
b11011 m
b11 n
1&
#420000
0&
#425000
b10 p
b10 o
b1 l
b100100 k
b1 n
1&
#430000
0&
#435000
b11 p
b10 n
1&
#440000
0&
#445000
1:
b111111 ;
b1 p
b111111 2
b111111 b
b111111 m
b11 n
1&
#450000
0&
#455000
0e
b11 p
b11 o
b0 l
b1001000 k
b1 n
1&
#460000
0&
#465000
b100 p
b11 n
1&
#470000
0&
#475000
b0 o
b10010000 k
b100 n
1&
#480000
0&
#485000
15
1&
#490000
0&
#495000
0!
1"
b111111 #
b111111 9
1&
#500000
0&
#505000
1B"
1~
1)"
0!"
1<"
0@"
1#"
1*"
0.
0^
1\
1C"
0A"
03
0R
1P
0X
b11110 B
b1110 1
b1110 >
b1110 C
1V
16"
04"
b10000 '"
b0 6
b0 z
b0 ""
b0 ("
0:"
1:
b111111 ;
0_
1]
0?"
0R"
0S
1Q
0Y
1W
17"
1="
0L"
b0 0
b0 F"
0O"
1[
b0 }
b0 %"
1Q"
1N
1T
12"
18"
1J"
1M"
b1111 %
b1111 +
b1111 =
b1111 @
b1111 a
b1111 d
b1111 y
b1111 |
b1111 E"
b1111 $
b1111 *
b1111 <
b1111 ?
b1111 `
b1111 c
b1111 q
b1111 t
b1111 x
b1111 {
b1111 $"
b1111 D"
b1111 T"
b1111 S"
1&
#510000
0&
#515000
1,
1'
1&
#520000
0&
#525000
1e
04
0:
b0 ;
b10 p
05
b1111 l
b1111 k
b0 2
b0 b
b0 m
b1 n
0,
0'
1&
#530000
0&
#535000
b11 p
b10 n
1&
#540000
0&
